xia_connector_mail/__init__.py
xia_connector_mail/connector.cpython-310-x86_64-linux-gnu.so
xia_connector_mail-0.0.4.dist-info/LICENSE.txt
xia_connector_mail-0.0.4.dist-info/METADATA
xia_connector_mail-0.0.4.dist-info/WHEEL
xia_connector_mail-0.0.4.dist-info/top_level.txt
xia_connector_mail-0.0.4.dist-info/RECORD
