Metadata-Version: 2.1
Name: xia-connector-mail
Version: 0.0.4
Summary: X-I-A Mail Connector
Home-page: https://develop.x-i-a.com/docs/xia-connector-mail/0.0.4/index.html
Author: X-I-A
Author-email: admin@x-i-a.com
Requires-Python: >=3.7
License-File: LICENSE.txt
Requires-Dist: requests
Requires-Dist: xia-meta
Requires-Dist: xia-meta-secret
